{
  "id": "0x010000450001C1C3",
  "title": "SEAFORT ORB / quiet on the island",
  "description": "(afterthought on silence and sounds)",
  "dialogueTree": [
    {
      "id": 45,
      "title": "Perception (Hearing): \"The dry grass crackles under your f...\"",
      "articyId": "0x010000450001C4F3",
      "text": "The dry grass crackles under your feet as you stop. Far away birds' wings touch the still surface of the sea...",
      "links": [
        {
          "id": 108,
          "title": "You: \"What is that flutter?\"",
          "articyId": "0x010000450001C502",
          "text": "What is that flutter?",
          "links": [
            {
              "id": 69,
              "title": "Perception (Hearing): \"The flock of quail departs; now mor...\"",
              "articyId": "0x010000450001C513",
              "text": "The flock of quail departs; now more than a hundred metres away... a hundred and two... a hundred and five...",
              "links": [
                {
                  "id": 53,
                  "title": "You: \"Underneath the flutter...\"",
                  "articyId": "0x010000450001C536",
                  "text": "Underneath the flutter...",
                  "links": [
                    {
                      "id": 13,
                      "title": "Perception (Hearing): \"On the islet? There is almost no wi...\"",
                      "articyId": "0x010000060000E511",
                      "text": "On the islet? There is almost no wind under the rain quietly falling on the reeds. Bulrushes swaying on the waterline, long dried leaves chafing against each other. The soft raindrops...",
                      "links": [
                        {
                          "id": 21,
                          "title": "Conceptualization: \"Like a silent orchestra tuning -- a...\"",
                          "articyId": "0x010000450001C545",
                          "text": "Like a silent orchestra tuning -- at the beginning of some major work.",
                          "links": [
                            {
                              "id": 2,
                              "title": "Shivers: \"Of great importance to the few who...\"",
                              "articyId": "0x010000450001C54C",
                              "text": "Of great importance to the few who attend.",
                              "links": [
                                {
                                  "id": 54,
                                  "title": "You: \"To the west...\"",
                                  "articyId": "0x010000450001C56D",
                                  "text": "To the west...",
                                  "links": [
                                    {
                                      "id": 61,
                                      "title": "Perception (Hearing): \"A silent hiss, sea air moving throu...\"",
                                      "articyId": "0x010000450001C597",
                                      "text": "A silent hiss, sea air moving through the needles of a pine tree.",
                                      "links": []
                                    }
                                  ]
                                },
                                {
                                  "id": 3,
                                  "title": "You: \"To the east...\"",
                                  "articyId": "0x010000450001C567",
                                  "text": "To the east...",
                                  "links": [
                                    {
                                      "id": 34,
                                      "title": "Perception (Hearing): \"The far away roar of the city, dist...\"",
                                      "articyId": "0x010000450001C58A",
                                      "text": "The far away roar of the city, distant like today's dream. Before it, the sound of sand. The low tide filtered through its grains... a bird tending to its feathers.",
                                      "links": [
                                        {
                                          "id": 62,
                                          "title": "Perception (Hearing): \"Raindrops fall on water, strangely...\"",
                                          "articyId": "0x010000450001C5BA",
                                          "text": "Raindrops fall on water, strangely quiet, forming circles in the distance...",
                                          "links": []
                                        },
                                        {
                                          "id": 63,
                                          "title": "Perception (Hearing): \"Snow falls on the water, melting aw...\"",
                                          "articyId": "0x010000450001C5C1",
                                          "text": "Snow falls on the water, melting away without even a whisper.",
                                          "links": []
                                        }
                                      ]
                                    }
                                  ]
                                },
                                {
                                  "id": 10,
                                  "title": "You: \"Ahead...\"",
                                  "articyId": "0x010000450001C561",
                                  "text": "Ahead...",
                                  "links": [
                                    {
                                      "id": 99,
                                      "title": "Perception (Hearing): \"A low hum. The air slowly moves thr...\"",
                                      "articyId": "0x010000450001C57C",
                                      "text": "A low hum. The air slowly moves through a concrete box -- through its ancient slits and cracks. Resonating. Hollow. A big building.",
                                      "links": []
                                    }
                                  ]
                                },
                                {
                                  "id": 35,
                                  "title": "You: \"Beyond that... further north...\"",
                                  "articyId": "0x010000450001C5A4",
                                  "text": "Beyond that... further north...",
                                  "links": [
                                    {
                                      "id": 11,
                                      "title": "Perception (Hearing): \"Air flows out of a pillbox window....\"",
                                      "articyId": "0x010000450001C583",
                                      "text": "Air flows out of a pillbox window. There is very little there. The air cossets flowers on a meadow? Absolute silence. Reeds motionless. Bulrushes motionless.",
                                      "links": [
                                        {
                                          "id": 88,
                                          "title": "Perception (Hearing): \"A flake of snow falls on an extingu...\"",
                                          "articyId": "0x010000450001C5ED",
                                          "text": "A flake of snow falls on an extinguished camp-fire. Hiss...",
                                          "links": []
                                        },
                                        {
                                          "id": 37,
                                          "title": "Perception (Hearing): \"A drop of rain falls on a black log...\"",
                                          "articyId": "0x010000450001C5D5",
                                          "text": "A drop of rain falls on a black log. Of an extinguished camp-fire.",
                                          "links": []
                                        }
                                      ]
                                    }
                                  ]
                                },
                                {
                                  "id": 16,
                                  "title": "You: \"Below the silence?\"",
                                  "articyId": "0x010000450001C5C9",
                                  "text": "Below the silence?",
                                  "links": [
                                    {
                                      "id": 97,
                                      "title": "Perception (Hearing): \"Col Do Ma Ma Daqua.\"",
                                      "articyId": "0x010000450001C5CF",
                                      "text": "Col Do Ma Ma Daqua.",
                                      "links": [
                                        {
                                          "id": 84,
                                          "title": "Inland Empire: \"We are way out now... Way out in th...\"",
                                          "articyId": "0x010000450001C622",
                                          "text": "We are way out now... Way out in the West.",
                                          "links": []
                                        }
                                      ]
                                    },
                                    {
                                      "id": 55,
                                      "title": "Perception (Hearing): \"A jitter. A sound impatient to happ...\"",
                                      "articyId": "0x010000450001C608",
                                      "text": "A jitter. A sound impatient to happen, but not yet in this world.",
                                      "links": [
                                        {
                                          "id": 83,
                                          "title": "Inland Empire: \"You hear some kind of limb fidget,...\"",
                                          "articyId": "0x010000450001C61B",
                                          "text": "You hear some kind of limb fidget, producing an imperceptible tick...",
                                          "links": [
                                            {
                                              "id": 74,
                                              "title": "Logic: \"No, it's just your imagination. You...\"",
                                              "articyId": "0x010000450001C629",
                                              "text": "No, it's just your imagination. You can't hear such things.",
                                              "links": []
                                            }
                                          ]
                                        }
                                      ]
                                    }
                                  ]
                                },
                                {
                                  "id": 101,
                                  "title": "You: \"\"Cuno...\"\"",
                                  "articyId": "0x010000890000256F",
                                  "text": "\"Cuno...\"",
                                  "links": [
                                    {
                                      "id": 5,
                                      "title": "Cuno: \"\"What?\"\"",
                                      "articyId": "0x0100008900002576",
                                      "text": "\"What?\"",
                                      "links": [
                                        {
                                          "id": 90,
                                          "title": "Pain Threshold: \"Momentarily the sounds are swept aw...\"",
                                          "articyId": "0x010000890000257D",
                                          "text": "Momentarily the sounds are swept away. Pain shoots up your right foot and into your groin...",
                                          "links": [
                                            {
                                              "id": 51,
                                              "title": "You: \"\"It's pretty silent on this island.\"\"",
                                              "articyId": "0x010000890000259D",
                                              "text": "\"It's pretty silent on this island.\"",
                                              "links": [
                                                {
                                                  "id": 107,
                                                  "title": "Cuno: \"He shrugs. \"Spooky-ass island. That...\"",
                                                  "articyId": "0x01000089000025BB",
                                                  "text": "He shrugs. \"Spooky-ass island. That's how it is on spooky-ass islands. Silent and shit.\"",
                                                  "links": [
                                                    {
                                                      "id": 76,
                                                      "title": "You: \"\"Mhm. Wait. I have to listen to one...\"",
                                                      "articyId": "0x01000089000025D8",
                                                      "text": "\"Mhm. Wait. I have to listen to one more thing.\"",
                                                      "links": []
                                                    }
                                                  ]
                                                }
                                              ]
                                            },
                                            {
                                              "id": 102,
                                              "title": "You: \"\"Have you noticed how quiet it is?\"\"",
                                              "articyId": "0x01000089000025A9",
                                              "text": "\"Have you noticed how quiet it is?\"",
                                              "links": [
                                                {
                                                  "id": 81,
                                                  "title": "Cuno: \"\"Yeah. Spooky-ass island. That's ho...\"",
                                                  "articyId": "0x01000089000025C1",
                                                  "text": "\"Yeah. Spooky-ass island. That's how it is on spooky-ass islands. Silent and shit.\"",
                                                  "links": []
                                                }
                                              ]
                                            },
                                            {
                                              "id": 75,
                                              "title": "You: \"\"It's really fucking silent on this...\"",
                                              "articyId": "0x01000089000025A3",
                                              "text": "\"It's really fucking silent on this island.\"",
                                              "links": [
                                                {
                                                  "id": 98,
                                                  "title": "Cuno: \"\"Fuckin' spooky, yeah. Is what it i...\"",
                                                  "articyId": "0x01000089000025C6",
                                                  "text": "\"Fuckin' spooky, yeah. Is what it is.\"",
                                                  "links": []
                                                }
                                              ]
                                            },
                                            {
                                              "id": 20,
                                              "title": "You: \"\"It... hurts a bit. Maybe the banda...\"",
                                              "articyId": "0x01000089000025AF",
                                              "text": "\"It... hurts a bit. Maybe the bandage is off?\"",
                                              "links": [
                                                {
                                                  "id": 43,
                                                  "title": "Cuno: \"He squints at you. \"Is that why we'...\"",
                                                  "articyId": "0x01000089000025CB",
                                                  "text": "He squints at you. \"Is that why we're stopping? So you can *bitch about the bandage*?\"",
                                                  "links": [
                                                    {
                                                      "id": 103,
                                                      "title": "You: \"\"Sorry. Let's move.\" [Leave.]\"",
                                                      "articyId": "0x01000089000025DE",
                                                      "text": "\"Sorry. Let's move.\" [Leave.]",
                                                      "links": []
                                                    },
                                                    {
                                                      "id": 44,
                                                      "title": "You: \"\"No, I was listening to something.\"\"",
                                                      "articyId": "0x01000089000025EF",
                                                      "text": "\"No, I was listening to something.\"",
                                                      "links": [
                                                        {
                                                          "id": 82,
                                                          "title": "Cuno: \"The kid shrugs. He sniffs, audibly...\"",
                                                          "articyId": "0x01000089000025EA",
                                                          "text": "The kid shrugs. He sniffs, audibly -- then, silence.",
                                                          "links": []
                                                        }
                                                      ]
                                                    }
                                                  ]
                                                }
                                              ]
                                            },
                                            {
                                              "id": 50,
                                              "title": "Pain Threshold: \"This is where a lesser man would st...\"",
                                              "articyId": "0x0100008900002588",
                                              "text": "This is where a lesser man would stop to think about the pain shooting up his right leg and into his groin -- not you, you're concentrated on how...",
                                              "links": []
                                            }
                                          ]
                                        }
                                      ]
                                    }
                                  ]
                                },
                                {
                                  "id": 46,
                                  "title": "You: \"\"Kim...\"\"",
                                  "articyId": "0x010000450001C576",
                                  "text": "\"Kim...\"",
                                  "links": [
                                    {
                                      "id": 67,
                                      "title": "Kim Kitsuragi: \"\"Yes?\"\"",
                                      "articyId": "0x010000450001C649",
                                      "text": "\"Yes?\"",
                                      "links": [
                                        {
                                          "id": 24,
                                          "title": "Pain Threshold: \"Momentarily the sounds are swept aw...\"",
                                          "articyId": "0x010000450001C9F2",
                                          "text": "Momentarily the sounds are swept away. Pain shoots up your right foot and into your groin...",
                                          "links": [
                                            {
                                              "id": 80,
                                              "title": "You: \"\"It's pretty silent on this island.\"\"",
                                              "articyId": "0x010000450001C656",
                                              "text": "\"It's pretty silent on this island.\"",
                                              "links": [
                                                {
                                                  "id": 33,
                                                  "title": "Kim Kitsuragi: \"\"It is -- is that why we're stoppin...\"",
                                                  "articyId": "0x010000450001C666",
                                                  "text": "\"It is -- is that why we're stopping?\"",
                                                  "links": [
                                                    {
                                                      "id": 85,
                                                      "title": "You: \"\"Sorry. Let's move.\" [Leave.]\"",
                                                      "articyId": "0x010000450001C683",
                                                      "text": "\"Sorry. Let's move.\" [Leave.]",
                                                      "links": []
                                                    },
                                                    {
                                                      "id": 89,
                                                      "title": "You: \"\"Mhm. Wait. I have to listen to one...\"",
                                                      "articyId": "0x010000450001C689",
                                                      "text": "\"Mhm. Wait. I have to listen to one more thing.\"",
                                                      "links": [
                                                        {
                                                          "id": 100,
                                                          "title": "Kim Kitsuragi: \"The lieutenant nods, in silence.\"",
                                                          "articyId": "0x010000450001C691",
                                                          "text": "The lieutenant nods, in silence.",
                                                          "links": []
                                                        }
                                                      ]
                                                    }
                                                  ]
                                                }
                                              ]
                                            },
                                            {
                                              "id": 12,
                                              "title": "You: \"\"Have you noticed how quiet it is?\"\"",
                                              "articyId": "0x010000450001C65C",
                                              "text": "\"Have you noticed how quiet it is?\"",
                                              "links": [
                                                {
                                                  "id": 106,
                                                  "title": "Kim Kitsuragi: \"\"I have -- is that why we're stoppi...\"",
                                                  "articyId": "0x010000450001C66E",
                                                  "text": "\"I have -- is that why we're stopping?\"",
                                                  "links": []
                                                }
                                              ]
                                            },
                                            {
                                              "id": 22,
                                              "title": "You: \"\"It's really fucking silent on this...\"",
                                              "articyId": "0x010000450001C650",
                                              "text": "\"It's really fucking silent on this island.\"",
                                              "links": []
                                            },
                                            {
                                              "id": 36,
                                              "title": "Pain Threshold: \"This is where a lesser man would st...\"",
                                              "articyId": "0x010000450001C9FF",
                                              "text": "This is where a lesser man would stop to think about the pain shooting up his right leg and into his groin -- not you, you're concentrated on how...",
                                              "links": [
                                                {
                                                  "id": 86,
                                                  "title": "You: \"\"It... hurts a bit. Maybe the banda...\"",
                                                  "articyId": "0x010000450001C9E0",
                                                  "text": "\"It... hurts a bit. Maybe the bandage is off?\"",
                                                  "links": [
                                                    {
                                                      "id": 23,
                                                      "title": "Kim Kitsuragi: \"\"It can happen -- is that why we're...\"",
                                                      "articyId": "0x010000450001C9E6",
                                                      "text": "\"It can happen -- is that why we're stopping?\"",
                                                      "links": [
                                                        {
                                                          "id": 105,
                                                          "title": "You: \"\"No, I was listening to something.\"\"",
                                                          "articyId": "0x010000450001CA12",
                                                          "text": "\"No, I was listening to something.\"",
                                                          "links": []
                                                        }
                                                      ]
                                                    }
                                                  ]
                                                }
                                              ]
                                            }
                                          ]
                                        }
                                      ]
                                    }
                                  ]
                                },
                                {
                                  "id": 104,
                                  "title": "You: \"[Open your eyes, stop listening.]\"",
                                  "articyId": "0x010000450001C642",
                                  "text": "[Open your eyes, stop listening.]",
                                  "links": []
                                }
                              ]
                            },
                            {
                              "id": 14,
                              "title": "Shivers: \"The great ghost of the air is holdi...\"",
                              "articyId": "0x010000450001C53E",
                              "text": "The great ghost of the air is holding its breath.",
                              "links": []
                            }
                          ]
                        }
                      ]
                    },
                    {
                      "id": 6,
                      "title": "Perception (Hearing): \"On the islet? There is almost no wi...\"",
                      "articyId": "0x010000060000E517",
                      "text": "On the islet? There is almost no wind, just snow quietly falling on the reeds. Bulrushes swaying on the waterline, long dried leaves chafing against each other.",
                      "links": []
                    },
                    {
                      "id": 31,
                      "title": "Perception (Hearing): \"On the islet? There is almost no wi...\"",
                      "articyId": "0x010000450001C51B",
                      "text": "On the islet? There is almost no wind, just the light movement of air through the reeds. Bulrushes swaying on the waterline, long dried leaves chafing against each other.",
                      "links": []
                    }
                  ]
                }
              ]
            }
          ]
        },
        {
          "id": 52,
          "title": "You: \"[Stop listening.]\"",
          "articyId": "0x010000450001C508",
          "text": "[Stop listening.]",
          "links": []
        }
      ]
    }
  ]
}